.DS_Store
HEDM_Toolkit/HEDM_Toolkit.py
HEDM_Toolkit/__init__.py
HEDM_Toolkit/utilities.py
HEDM_Toolkit/Demo/config.yml
HEDM_Toolkit/Demo/nugget_2_frames_for_test.h5
HEDM_Toolkit/Demo/nugget_layer0_det0_50bg.par
HEDM_Toolkit/Demo/nugget_layer0_det0_for_test.flt
HEDM_Toolkit/data/image_test.png
HEDM_Toolkit/data/imaged11_dx.edf
HEDM_Toolkit/data/imaged11_dy.edf
HEDM_Toolkit/scripts/clean_flt.py
HEDM_Toolkit/scripts/fitting.py
HEDM_Toolkit/scripts/gen_flt.py
HEDM_Toolkit/scripts/indexing.py
HEDM_Toolkit/scripts/sparse_h5.py
HEDM_Toolkit-0.4.3.dist-info/METADATA
HEDM_Toolkit-0.4.3.dist-info/WHEEL
HEDM_Toolkit-0.4.3.dist-info/entry_points.txt
HEDM_Toolkit-0.4.3.dist-info/top_level.txt
HEDM_Toolkit-0.4.3.dist-info/RECORD
